pyobs_zaber/__init__.py
pyobs_zaber/zaberdriver.py
pyobs_zaber/zabermodeselector.py
pyobs_zaber-1.1.0.dist-info/METADATA
pyobs_zaber-1.1.0.dist-info/WHEEL
pyobs_zaber-1.1.0.dist-info/licenses/LICENSE
pyobs_zaber-1.1.0.dist-info/RECORD
