Metadata-Version: 2.4
Name: pyobs-zaber
Version: 1.1.0
Summary: pyobs model for Zaber motors
Author-email: Leon Meerwart <leon.meerwart@uni-goettingen.de>
License-Expression: MIT
License-File: LICENSE
Requires-Python: <3.12,>=3.9
Requires-Dist: pyobs-core<2,>=1
Requires-Dist: zaber-motion<5,>=4.7.0
